convnet_morpho/__init__.py
convnet_morpho/about_convnet_morpho.py
convnet_morpho/cluster.py
convnet_morpho/convnet.py
convnet_morpho/crop.py
convnet_morpho/finished
convnet_morpho/load_brain1_new.py
convnet_morpho/load_brain2_new.py
convnet_morpho/load_seqfishplus_new.py
convnet_morpho/path.py
convnet_morpho/reader.py
convnet_morpho-1.0.1.dist-info/METADATA
convnet_morpho-1.0.1.dist-info/WHEEL
convnet_morpho-1.0.1.dist-info/entry_points.txt
convnet_morpho-1.0.1.dist-info/top_level.txt
convnet_morpho-1.0.1.dist-info/RECORD
