Metadata-Version: 2.1
Name: convnet-morpho
Version: 1.0.1
Summary: convnet-morpho is a cell morphology analysis library
Home-page: https://bitbucket.org/qzhudfci/convnet.morpho
Author: Qian Zhu
Author-email: qian_zhu@dfci.harvard.edu
License: UNKNOWN
Platform: UNKNOWN
Classifier: Programming Language :: Python :: 3
Classifier: License :: OSI Approved :: MIT License
Classifier: Operating System :: OS Independent
Requires-Python: >=3.6
Requires-Dist: scipy
Requires-Dist: numpy
Requires-Dist: pandas
Requires-Dist: seaborn
Requires-Dist: matplotlib
Requires-Dist: jsbeautifier
